<annotation>
	<folder>train</folder>
	<filename>20230430_153341.jpg</filename>
	<path>C:\Users\samca\Projects\TF2\models\research\object_detection\DICE\train\20230430_153341.jpg</path>
	<source>
		<database>Unknown</database>
	</source>
	<size>
		<width>1800</width>
		<height>4000</height>
		<depth>3</depth>
	</size>
	<segmented>0</segmented>
	<object>
		<name>ten</name>
		<pose>Unspecified</pose>
		<truncated>0</truncated>
		<difficult>0</difficult>
		<bndbox>
			<xmin>589</xmin>
			<ymin>973</ymin>
			<xmax>954</xmax>
			<ymax>1351</ymax>
		</bndbox>
	</object>
	<object>
		<name>one</name>
		<pose>Unspecified</pose>
		<truncated>0</truncated>
		<difficult>0</difficult>
		<bndbox>
			<xmin>67</xmin>
			<ymin>1647</ymin>
			<xmax>480</xmax>
			<ymax>2038</ymax>
		</bndbox>
	</object>
	<object>
		<name>eleven</name>
		<pose>Unspecified</pose>
		<truncated>0</truncated>
		<difficult>0</difficult>
		<bndbox>
			<xmin>449</xmin>
			<ymin>2051</ymin>
			<xmax>806</xmax>
			<ymax>2417</ymax>
		</bndbox>
	</object>
	<object>
		<name>eight</name>
		<pose>Unspecified</pose>
		<truncated>0</truncated>
		<difficult>0</difficult>
		<bndbox>
			<xmin>1045</xmin>
			<ymin>1890</ymin>
			<xmax>1423</xmax>
			<ymax>2256</ymax>
		</bndbox>
	</object>
	<object>
		<name>four</name>
		<pose>Unspecified</pose>
		<truncated>0</truncated>
		<difficult>0</difficult>
		<bndbox>
			<xmin>1232</xmin>
			<ymin>2160</ymin>
			<xmax>1576</xmax>
			<ymax>2521</ymax>
		</bndbox>
	</object>
</annotation>
